README.md
setup.py
gptools/__init__.py
pygptools.egg-info/PKG-INFO
pygptools.egg-info/SOURCES.txt
pygptools.egg-info/dependency_links.txt
pygptools.egg-info/top_level.txt